LICENSE
MANIFEST.in
README
setup.py
ita/__init__.py
ita/array.py
ita/bench.py
ita/excheck.py
ita/global_vars.py
ita/plot.py
ita.egg-info/PKG-INFO
ita.egg-info/SOURCES.txt
ita.egg-info/dependency_links.txt
ita.egg-info/requires.txt
ita.egg-info/top_level.txt
test/__init__.py
test/array.py
test/bench.py
test/excheck.py
test/ita_main.py
test/plot.py
test/test.py