Metadata-Version: 1.1
Name: ita
Version: 0.4.2
Summary: support package for "introduction to algorithm" lecture
Home-page: https://lecture.ecc.u-tokyo.ac.jp/johzu/joho-kagaku/
Author: Akimasa Morihata
Author-email: morihata@graco.c.u-tokyo.ac.jp
License: You are free to copy, redistribute, modify, and build upon the
